ccda_cli/__init__.py
ccda_cli/cli.py
ccda_cli/config.py
ccda_cli/analysis/__init__.py
ccda_cli/analysis/pipeline.py
ccda_cli/cache/__init__.py
ccda_cli/cache/manager.py
ccda_cli/core/__init__.py
ccda_cli/core/git.py
ccda_cli/core/http.py
ccda_cli/discovery/__init__.py
ccda_cli/discovery/purl.py
ccda_cli/discovery/resolver.py
ccda_cli/enrichment/__init__.py
ccda_cli/enrichment/company.py
ccda_cli/metrics/__init__.py
ccda_cli/metrics/git.py
ccda_cli/metrics/github.py
ccda_cli/report/__init__.py
ccda_cli/report/generator.py
ccda_cli/reports/__init__.py
ccda_cli/scanner/__init__.py
ccda_cli/scanner/tarball.py
ccda_cli/scoring/__init__.py
ccda_cli/scoring/burnout.py
ccda_cli/scoring/health.py
ccda_cli-0.2.2.dist-info/METADATA
ccda_cli-0.2.2.dist-info/WHEEL
ccda_cli-0.2.2.dist-info/entry_points.txt
ccda_cli-0.2.2.dist-info/licenses/AUTHORS.md
ccda_cli-0.2.2.dist-info/licenses/LICENSE
ccda_cli-0.2.2.dist-info/RECORD
