Metadata-Version: 2.4
Name: ccda-cli
Version: 0.2.2
Summary: CLI tool for collecting software supply chain security metrics
Project-URL: Homepage, https://github.com/semcl/ccda-cli
Project-URL: Documentation, https://ccda.semcl.one
Project-URL: Repository, https://github.com/semcl/ccda-cli
Author-email: SEMCL <info@semcl.one>
License-Expression: AGPL-3.0-or-later
License-File: AUTHORS.md
License-File: LICENSE
Keywords: metrics,purl,sbom,security,supply-chain
Classifier: Development Status :: 3 - Alpha
Classifier: Environment :: Console
Classifier: Intended Audience :: Developers
Classifier: License :: OSI Approved :: GNU Affero General Public License v3 or later (AGPLv3+)
Classifier: Programming Language :: Python :: 3
Classifier: Programming Language :: Python :: 3.10
Classifier: Programming Language :: Python :: 3.11
Classifier: Programming Language :: Python :: 3.12
Classifier: Topic :: Security
Classifier: Topic :: Software Development :: Libraries
Requires-Python: >=3.10
Requires-Dist: anyio>=4.0
Requires-Dist: click>=8.1.0
Requires-Dist: httpx>=0.27.0
Requires-Dist: osslili>=0.1.0
Requires-Dist: packageurl-python>=0.15.0
Requires-Dist: purl2src>=0.1.0
Requires-Dist: pydantic>=2.0
Requires-Dist: pyyaml>=6.0
Requires-Dist: rich>=13.0
Provides-Extra: dev
Requires-Dist: mypy>=1.8; extra == 'dev'
Requires-Dist: pytest-asyncio>=0.23; extra == 'dev'
Requires-Dist: pytest-cov>=4.0; extra == 'dev'
Requires-Dist: pytest>=8.0; extra == 'dev'
Requires-Dist: ruff>=0.1.0; extra == 'dev'
Requires-Dist: types-pyyaml; extra == 'dev'
